CHANGES.rst
MANIFEST.in
README.rst
buildout.cfg
requirements-coverage.txt
requirements-tests.txt
setup.py
docs/LICENSE.GPL
docs/LICENSE.txt
src/EXTERNALS.txt
src/Products/__init__.py
src/Products.MeetingNamur.egg-info/PKG-INFO
src/Products.MeetingNamur.egg-info/SOURCES.txt
src/Products.MeetingNamur.egg-info/dependency_links.txt
src/Products.MeetingNamur.egg-info/namespace_packages.txt
src/Products.MeetingNamur.egg-info/not-zip-safe
src/Products.MeetingNamur.egg-info/requires.txt
src/Products.MeetingNamur.egg-info/top_level.txt
src/Products/MeetingNamur/README.txt
src/Products/MeetingNamur/__init__.py
src/Products/MeetingNamur/adapters.py
src/Products/MeetingNamur/config.py
src/Products/MeetingNamur/configure.zcml
src/Products/MeetingNamur/events.py
src/Products/MeetingNamur/events.zcml
src/Products/MeetingNamur/interfaces.py
src/Products/MeetingNamur/overrides.zcml
src/Products/MeetingNamur/profiles.zcml
src/Products/MeetingNamur/refresh.txt
src/Products/MeetingNamur/setuphandlers.py
src/Products/MeetingNamur/testing.py
src/Products/MeetingNamur/testing.zcml
src/Products/MeetingNamur/version.txt
src/Products/MeetingNamur/Extensions/__init__.py
src/Products/MeetingNamur/browser/__init__.py
src/Products/MeetingNamur/browser/configure.zcml
src/Products/MeetingNamur/browser/itemcertifiedsignatures.py
src/Products/MeetingNamur/browser/overrides.py
src/Products/MeetingNamur/browser/templates/display_certified_signatures.pt
src/Products/MeetingNamur/locales/PloneMeeting.pot
src/Products/MeetingNamur/locales/imio.actionspanel.pot
src/Products/MeetingNamur/locales/imio.history.pot
src/Products/MeetingNamur/locales/plone.pot
src/Products/MeetingNamur/locales/sync_pos.sh
src/Products/MeetingNamur/locales/de/LC_MESSAGES/PloneMeeting.po
src/Products/MeetingNamur/locales/de/LC_MESSAGES/imio.actionspanel.po
src/Products/MeetingNamur/locales/de/LC_MESSAGES/imio.history.po
src/Products/MeetingNamur/locales/de/LC_MESSAGES/plone.po
src/Products/MeetingNamur/locales/en/LC_MESSAGES/PloneMeeting.po
src/Products/MeetingNamur/locales/en/LC_MESSAGES/imio.actionspanel.po
src/Products/MeetingNamur/locales/en/LC_MESSAGES/imio.history.po
src/Products/MeetingNamur/locales/en/LC_MESSAGES/plone.po
src/Products/MeetingNamur/locales/es/LC_MESSAGES/PloneMeeting.po
src/Products/MeetingNamur/locales/es/LC_MESSAGES/imio.actionspanel.po
